serverwamp/__init__.py
serverwamp/application.py
serverwamp/connection.py
serverwamp/context.py
serverwamp/events.py
serverwamp/helpers.py
serverwamp/json.py
serverwamp/protocol.py
serverwamp/py.typed
serverwamp/routing.py
serverwamp/rpc.py
serverwamp/session.py
serverwamp/adapters/__init__.py
serverwamp/adapters/aiohttp.py
serverwamp/adapters/anyio.py
serverwamp/adapters/asgi.py
serverwamp/adapters/async_base.py
serverwamp/adapters/asyncio.py
serverwamp/adapters/trio.py
serverwamp-1.1.2.dist-info/LICENSE.md
serverwamp-1.1.2.dist-info/METADATA
serverwamp-1.1.2.dist-info/WHEEL
serverwamp-1.1.2.dist-info/top_level.txt
serverwamp-1.1.2.dist-info/RECORD
