Metadata-Version: 2.1
Name: serverwamp
Version: 1.1.2
Summary: Components that add Web Application Messaging Protocol features to WebSocket servers.
Home-page: https://github.com/JustinTArthur/serverwamp
Author: Justin Turner Arthur
Author-email: justinarthur@gmail.com
License: MIT
Project-URL: Documentation, https://serverwamp.readthedocs.io/
Keywords: WAMP,WebSockets,aiohttp,RPC,pubsub,broker,dealer,ASGI
Platform: UNKNOWN
Classifier: Programming Language :: Python
Classifier: Programming Language :: Python :: 3
Classifier: Programming Language :: Python :: 3.6
Classifier: Programming Language :: Python :: 3.7
Classifier: Development Status :: 3 - Alpha
Classifier: Intended Audience :: Developers
Classifier: License :: OSI Approved :: MIT License
Classifier: Topic :: Software Development :: Libraries :: Python Modules
Classifier: Topic :: Internet
Classifier: Framework :: AsyncIO
Classifier: Framework :: Trio
Requires-Python: >=3.6
License-File: LICENSE.md
Requires-Dist: msgpack (~=1.0.0)
Requires-Dist: dataclasses (~=0.6) ; python_version < "3.7"
Provides-Extra: docs
Requires-Dist: Sphinx (==3.0.3) ; extra == 'docs'
